bpkio_cli/__init__.py
bpkio_cli/__main__.py
bpkio_cli/app.py
bpkio_cli/assets/C3-C4.wav
bpkio_cli/assets/C4-C3.wav
bpkio_cli/assets/C4-C5.wav
bpkio_cli/assets/C4-G4.wav
bpkio_cli/assets/C5-C4.wav
bpkio_cli/assets/E4-E4.wav
bpkio_cli/assets/G4-C4.wav
bpkio_cli/click_mods/__init__.py
bpkio_cli/click_mods/accepts_plugins_group.py
bpkio_cli/click_mods/accepts_shortcuts.py
bpkio_cli/click_mods/default_last_command.py
bpkio_cli/click_mods/forwarder_group.py
bpkio_cli/click_mods/option_eat_all.py
bpkio_cli/click_mods/plugin_commands.py
bpkio_cli/click_mods/resource_commands.py
bpkio_cli/click_options/__init__.py
bpkio_cli/click_options/admin.py
bpkio_cli/click_options/archive.py
bpkio_cli/click_options/dash.py
bpkio_cli/click_options/display_mode.py
bpkio_cli/click_options/list.py
bpkio_cli/click_options/list_format.py
bpkio_cli/click_options/monitor.py
bpkio_cli/click_options/options.py
bpkio_cli/click_options/poll.py
bpkio_cli/click_options/read.py
bpkio_cli/click_options/save.py
bpkio_cli/click_options/search.py
bpkio_cli/click_options/slots.py
bpkio_cli/click_options/urls.py
bpkio_cli/commands/__init__.py
bpkio_cli/commands/archive.bak
bpkio_cli/commands/archive.py
bpkio_cli/commands/categories.py
bpkio_cli/commands/configure.py
bpkio_cli/commands/consumption.py
bpkio_cli/commands/creators/ad_insertion.py
bpkio_cli/commands/creators/categories.py
bpkio_cli/commands/creators/services.py
bpkio_cli/commands/creators/slot_iterators.py
bpkio_cli/commands/creators/sources.py
bpkio_cli/commands/creators/virtual_channel.py
bpkio_cli/commands/creators/virtual_channel_populate.py
bpkio_cli/commands/creators/virtual_channel_slot.py
bpkio_cli/commands/doctor.py
bpkio_cli/commands/hello.py
bpkio_cli/commands/memory.py
bpkio_cli/commands/misc/compatibility_check.py
bpkio_cli/commands/package.py
bpkio_cli/commands/plugins.py
bpkio_cli/commands/profiles.py
bpkio_cli/commands/recorder.py
bpkio_cli/commands/services.py
bpkio_cli/commands/sessions.py
bpkio_cli/commands/source_check.py
bpkio_cli-3.1.0.dist-info/METADATA
bpkio_cli-3.1.0.dist-info/WHEEL
bpkio_cli-3.1.0.dist-info/entry_points.txt
bpkio_cli-3.1.0.dist-info/licenses/LICENSE.md
bpkio_cli-3.1.0.dist-info/RECORD
