Metadata-Version: 2.4
Name: bpkio-cli
Version: 3.1.0
Summary: A command line interface to the broadpeak.io APIs, with additional helpers
License-File: LICENSE.md
Author: Fabre Lambeau
Author-email: fabre.lambeau@broadpeak.tv
Requires-Python: >=3.10,<3.14
Classifier: Programming Language :: Python :: 3
Classifier: Programming Language :: Python :: 3.10
Classifier: Programming Language :: Python :: 3.11
Classifier: Programming Language :: Python :: 3.12
Classifier: Programming Language :: Python :: 3.13
Requires-Dist: arrow (>=1.2.3,<2.0.0)
Requires-Dist: boto3 (>=1.28.74,<2.0.0)
Requires-Dist: bpkio-python-sdk (>=3.1.0,<4.0.0)
Requires-Dist: chafa-py (>=1.1.2,<2.0.0)
Requires-Dist: click (>=8.3.1,<9.0.0)
Requires-Dist: click-complete-fig (>=1.1.1,<2.0.0)
Requires-Dist: cloup (>=3.0.7,<4.0.0)
Requires-Dist: colorama (>=0.4.6,<0.5.0)
Requires-Dist: dash (>=3.0.4,<4.0.0)
Requires-Dist: dash-bootstrap-components (>=2.0.3,<3.0.0)
Requires-Dist: dateparser (>=1.1.8,<2.0.0)
Requires-Dist: diskcache (>=5.4.0,<6.0.0)
Requires-Dist: ffmpeg-python (>=0.2.0,<0.3.0)
Requires-Dist: haralyzer (>=2.4.0,<3.0.0)
Requires-Dist: inquirerpy (>=0.3.4,<0.4.0)
Requires-Dist: loguru (>=0.7.2,<0.8.0)
Requires-Dist: m3u8 (>=4.1.0,<5.0.0)
Requires-Dist: packaging (>=24.0,<25.0)
Requires-Dist: pandas (>=2.3.0,<3.0.0)
Requires-Dist: pillow (>=10.2.0,<11.0.0)
Requires-Dist: plotly (>=6.1.2,<7.0.0)
Requires-Dist: progressbar2 (>=4.2.0,<5.0.0)
Requires-Dist: prompt-toolkit (>=3.0.43,<4.0.0)
Requires-Dist: pygments (>=2.15.1,<3.0.0)
Requires-Dist: pytimeparse (>=1.1.8,<2.0.0)
Requires-Dist: rich (>=13.7.1,<14.0.0)
Requires-Dist: setuptools (>=67.6.1,<68.0.0)
Requires-Dist: tabulated (>=0.10.0,<0.11.0)
Requires-Dist: threefive3 (>=3.0.19,<4.0.0)
Requires-Dist: tomlkit (>=0.13.2,<0.14.0)
Requires-Dist: trace-shrink (>=2.0.0,<3.0.0)
